{
    "KPlugin": {
        "Authors": [
            {
                "Email": "jowenn@kde.org",
                "Name": "Joseph Wenninger",
                "Name[az]": "Joseph Wenninger",
                "Name[ca@valencia]": "Joseph Wenninger",
                "Name[ca]": "Joseph Wenninger",
                "Name[cs]": "Joseph Wenninger",
                "Name[de]": "Joseph Wenninger",
                "Name[el]": "Joseph Wenninger",
                "Name[en_GB]": "Joseph Wenninger",
                "Name[es]": "Joseph Wenninger",
                "Name[eu]": "Joseph Wenninger",
                "Name[fi]": "Joseph Wenninger",
                "Name[fr]": "Joseph Wenninger",
                "Name[ia]": "Joseph Wenninger",
                "Name[it]": "Joseph Wenninger",
                "Name[ko]": "Joseph Wenninger",
                "Name[nl]": "Joseph Wenninger",
                "Name[pl]": "Joseph Wenninger",
                "Name[pt]": "Joseph Wenninger",
                "Name[sl]": "Joseph Wenninger",
                "Name[sv]": "Joseph Wenninger",
                "Name[uk]": "Joseph Wenninger",
                "Name[vi]": "Joseph Wenninger",
                "Name[x-test]": "xxJoseph Wenningerxx",
                "Name[zh_CN]": "Joseph Wenninger"
            }
        ],
        "Category": "Utilities",
        "Description": "Kate Session Launcher",
        "Description[az]": "Kate sessiya başladıcısı",
        "Description[ca@valencia]": "Llançador de la sessió del Kate",
        "Description[ca]": "Llançador de la sessió del Kate",
        "Description[cs]": "Spouštěč sezení Kate",
        "Description[de]": "Kate-Sitzung starten",
        "Description[el]": "Εκτελεστής συνεδρίας kate",
        "Description[en_GB]": "Kate Session Launcher",
        "Description[es]": "Lanzador de sesiones de Kate",
        "Description[eu]": "Kate saioaren abiarazlea",
        "Description[fi]": "Kate-istuntokäynnistin",
        "Description[fr]": "Lanceur de sessions pour Kate",
        "Description[ia]": "Lanceator de session de Kate",
        "Description[it]": "Avviatore delle sessioni di Kate",
        "Description[ko]": "Kate 세션 실행기",
        "Description[nl]": "Kate sessiestarter",
        "Description[pl]": "Uruchamia sesję Kate",
        "Description[pt]": "Lançador de Sessões do Kate",
        "Description[sl]": "Zaganjalnik seje Kate",
        "Description[sv]": "Kate sessionsstart",
        "Description[uk]": "Запуск сеансів Kate",
        "Description[vi]": "Trình khởi chạy phiên Kate",
        "Description[x-test]": "xxKate Session Launcherxx",
        "Description[zh_CN]": "Kate 会话启动器",
        "Icon": "kate",
        "Id": "org.kde.plasma.katesessions",
        "License": "GPL-2.0+",
        "Name": "Kate Sessions",
        "Name[az]": "Kate sessiyaları",
        "Name[ca@valencia]": "Sessions del Kate",
        "Name[ca]": "Sessions del Kate",
        "Name[cs]": "Sezení Kate",
        "Name[de]": "Kate-Sitzungen",
        "Name[el]": "Συνεδρίες kate",
        "Name[en_GB]": "Kate Sessions",
        "Name[es]": "Sesiones de Kate",
        "Name[eu]": "Katen saioak",
        "Name[fi]": "Kate-istunnot",
        "Name[fr]": "Sessions de Kate",
        "Name[ia]": "Sessiones de Kate",
        "Name[it]": "Sessioni di Kate",
        "Name[ko]": "Kate 세션",
        "Name[nl]": "Kate-sessies",
        "Name[pl]": "Sesje Kate",
        "Name[pt]": "Sessões do Kate",
        "Name[pt_BR]": "Sessões do Kate",
        "Name[sk]": "Kate sedenia",
        "Name[sl]": "Seje Kate",
        "Name[sv]": "Kate-sessioner",
        "Name[uk]": "Сеанси Kate",
        "Name[vi]": "Các phiên Kate",
        "Name[x-test]": "xxKate Sessionsxx",
        "Name[zh_CN]": "Kate 会话",
        "ServiceTypes": [
            "Plasma/Applet"
        ],
        "Version": "1.0"
    },
    "X-Plasma-API": "declarativeappletscript",
    "X-Plasma-MainScript": "ui/katesessions.qml",
    "X-Plasma-NotificationArea": "true"
}
